{
  "license": [
    {
      "name": "rubyzxy",
      "rs": "STP_Level",
      "key": "STP:2nd3mylEmZ",
      "dc": "https://discord.gg/hWdwTnUyUt"
    },
    {
      "name": "jaoblue",
      "rs": "STP_Level",
      "key": "STP:bYU9wPGAKE",
      "dc": "https://discord.gg/hWdwTnUyUt"
    },
    {
      "name": "chelyyy8028",
      "rs": "STP_Level",
      "key": "STP:m4ttX9g48i",
      "dc": "https://discord.gg/hWdwTnUyUt"
    },
    {
      "name": "chouxga",
      "rs": "STP_Level",
      "key": "STP:Xiip3bvsTU",
      "dc": "https://discord.gg/hWdwTnUyUt"
    }
  ]
}
